<?xml version="1.0" encoding="UTF-8"?>

<!-- =====================================================================
LogSeverityEnumAi.xml
Generated by fpp-to-xml
====================================================================== -->
<enum namespace="Fw" name="LogSeverity" serialize_type="I32" default="FATAL">
  <comment>
  Enum representing event severity
  </comment>
  <item name="FATAL" value="1" comment="A fatal non-recoverable event"/>
  <item name="WARNING_HI" value="2" comment="A serious but recoverable event"/>
  <item name="WARNING_LO" value="3" comment="A less serious but recoverable event"/>
  <item name="COMMAND" value="4" comment="An activity related to commanding"/>
  <item name="ACTIVITY_HI" value="5" comment="Important informational events"/>
  <item name="ACTIVITY_LO" value="6" comment="Less important informational events"/>
  <item name="DIAGNOSTIC" value="7" comment="Software diagnostic events"/>
</enum>
